approck_sqlalchemy_query_builder/__init__.py
approck_sqlalchemy_query_builder/types.py
approck_sqlalchemy_query_builder-1.0.3.dist-info/METADATA
approck_sqlalchemy_query_builder-1.0.3.dist-info/WHEEL
approck_sqlalchemy_query_builder-1.0.3.dist-info/RECORD
