Metadata-Version: 2.1
Name: approck-sqlalchemy-query-builder
Version: 1.0.3
Summary: 
Author: Aleksey Dalekin
Author-email: ald@approck.pro
Requires-Python: >=3.10,<4.0
Classifier: Programming Language :: Python :: 3
Classifier: Programming Language :: Python :: 3.10
Classifier: Programming Language :: Python :: 3.11
Classifier: Programming Language :: Python :: 3.12
Requires-Dist: SQLAlchemy[mypy] (>=2.0.0)
Requires-Dist: pydantic (>=2.4.1,<3.0.0)
Requires-Dist: python-dateutil (>=2.8.2,<3.0.0)
